[{"ID":102,"site":17,"name":"Maxin Rios &#8211; Flautist","date":"2022-06-07 11:38:00","status":"publish","editor":"elementor","tags":[],"categories":["musician","personal-site"],"is_pro":false,"views":32,"downloads":32,"palette":["#df123d","#af0e30","#330a13","#565253","#f9f6f6","","#f3eaec","","",""],"typography":{"slug":"typo-default","global":{"font":"Inter","weight":"regular","size":"16","line":"1.6","letter":"","word":""},"heading":{"font":"Tiro Kannada","weight":"regular","size":"","line":"1.6","letter":"","word":""}},"plugins":[{"name":"Elementor","slug":"elementor","init":"elementor\/elementor.php"},{"name":"Contact Form 7","slug":"contact-form-7","init":"contact-form-7\/wp-contact-form-7.php"},{"name":"MC4WP: Mailchimp for WordPress","slug":"mailchimp-for-wp","init":"mailchimp-for-wp\/mailchimp-for-wp.php"}],"previews":{"small":{"src":"https:\/\/demo.themeoo.com\/wp-content\/uploads\/2022\/06\/flute-artist.jpg","loading":"lazy","srcset":"https:\/\/demo.themeoo.com\/wp-content\/uploads\/2022\/06\/flute-artist.jpg 1108w, https:\/\/demo.themeoo.com\/wp-content\/uploads\/2022\/06\/flute-artist-258x300.jpg 258w, https:\/\/demo.themeoo.com\/wp-content\/uploads\/2022\/06\/flute-artist-880x1024.jpg 880w, https:\/\/demo.themeoo.com\/wp-content\/uploads\/2022\/06\/flute-artist-768x894.jpg 768w, https:\/\/demo.themeoo.com\/wp-content\/uploads\/2022\/06\/flute-artist-400x466.jpg 400w, https:\/\/demo.themeoo.com\/wp-content\/uploads\/2022\/06\/flute-artist-259x302.jpg 259w, https:\/\/demo.themeoo.com\/wp-content\/uploads\/2022\/06\/flute-artist-554x645.jpg 554w","sizes":"(max-width: 1108px) 100vw, 1108px","width":"1108","height":"1290"},"large":{"src":"https:\/\/demo.themeoo.com\/wp-content\/uploads\/2022\/06\/flute-artist.jpg","loading":"lazy","srcset":"https:\/\/demo.themeoo.com\/wp-content\/uploads\/2022\/06\/flute-artist.jpg 1108w, https:\/\/demo.themeoo.com\/wp-content\/uploads\/2022\/06\/flute-artist-258x300.jpg 258w, https:\/\/demo.themeoo.com\/wp-content\/uploads\/2022\/06\/flute-artist-880x1024.jpg 880w, https:\/\/demo.themeoo.com\/wp-content\/uploads\/2022\/06\/flute-artist-768x894.jpg 768w, https:\/\/demo.themeoo.com\/wp-content\/uploads\/2022\/06\/flute-artist-400x466.jpg 400w, https:\/\/demo.themeoo.com\/wp-content\/uploads\/2022\/06\/flute-artist-259x302.jpg 259w, https:\/\/demo.themeoo.com\/wp-content\/uploads\/2022\/06\/flute-artist-554x645.jpg 554w","sizes":"(max-width: 1108px) 100vw, 1108px","width":"1108","height":"1290"}},"preview":"https:\/\/demo.themeoo.com\/flute-artist\/?utm_source=ayyash-studio&utm_medium=wp-dash&utm_campaign=preview"},{"ID":90,"site":11,"name":"Voice &#8211; Podcast Website","date":"2022-06-07 11:25:04","status":"publish","editor":"elementor","tags":[],"categories":["blog","podcast"],"is_pro":false,"views":25,"downloads":25,"palette":["#f22e32","#a92023","#19223d","#313950","#f4f5f6","","","","",""],"typography":{"slug":"typo-default","global":{"font":"Sora","weight":"regular","size":"16","line":"1.6","letter":"","word":""},"heading":{"font":"Sora","weight":"700","size":"","line":"1.3","letter":"","word":""}},"plugins":[{"name":"Elementor","slug":"elementor","init":"elementor\/elementor.php"},{"name":"Contact Form 7","slug":"contact-form-7","init":"contact-form-7\/wp-contact-form-7.php"},{"name":"MC4WP: Mailchimp for WordPress","slug":"mailchimp-for-wp","init":"mailchimp-for-wp\/mailchimp-for-wp.php"}],"previews":{"small":{"src":"https:\/\/demo.themeoo.com\/wp-content\/uploads\/2022\/06\/voice-podcast-website.jpg","loading":"lazy","srcset":"https:\/\/demo.themeoo.com\/wp-content\/uploads\/2022\/06\/voice-podcast-website.jpg 1108w, https:\/\/demo.themeoo.com\/wp-content\/uploads\/2022\/06\/voice-podcast-website-258x300.jpg 258w, https:\/\/demo.themeoo.com\/wp-content\/uploads\/2022\/06\/voice-podcast-website-880x1024.jpg 880w, https:\/\/demo.themeoo.com\/wp-content\/uploads\/2022\/06\/voice-podcast-website-768x894.jpg 768w, https:\/\/demo.themeoo.com\/wp-content\/uploads\/2022\/06\/voice-podcast-website-400x466.jpg 400w, https:\/\/demo.themeoo.com\/wp-content\/uploads\/2022\/06\/voice-podcast-website-259x302.jpg 259w, https:\/\/demo.themeoo.com\/wp-content\/uploads\/2022\/06\/voice-podcast-website-554x645.jpg 554w","sizes":"(max-width: 1108px) 100vw, 1108px","width":"1108","height":"1290"},"large":{"src":"https:\/\/demo.themeoo.com\/wp-content\/uploads\/2022\/06\/voice-podcast-website.jpg","loading":"lazy","srcset":"https:\/\/demo.themeoo.com\/wp-content\/uploads\/2022\/06\/voice-podcast-website.jpg 1108w, https:\/\/demo.themeoo.com\/wp-content\/uploads\/2022\/06\/voice-podcast-website-258x300.jpg 258w, https:\/\/demo.themeoo.com\/wp-content\/uploads\/2022\/06\/voice-podcast-website-880x1024.jpg 880w, https:\/\/demo.themeoo.com\/wp-content\/uploads\/2022\/06\/voice-podcast-website-768x894.jpg 768w, https:\/\/demo.themeoo.com\/wp-content\/uploads\/2022\/06\/voice-podcast-website-400x466.jpg 400w, https:\/\/demo.themeoo.com\/wp-content\/uploads\/2022\/06\/voice-podcast-website-259x302.jpg 259w, https:\/\/demo.themeoo.com\/wp-content\/uploads\/2022\/06\/voice-podcast-website-554x645.jpg 554w","sizes":"(max-width: 1108px) 100vw, 1108px","width":"1108","height":"1290"}},"preview":"https:\/\/demo.themeoo.com\/podcast\/?utm_source=ayyash-studio&utm_medium=wp-dash&utm_campaign=preview"},{"ID":93,"site":8,"name":"Bagency Digital Agency","date":"2022-06-07 11:18:30","status":"publish","editor":"elementor","tags":[],"categories":["agency","business"],"is_pro":false,"views":25,"downloads":25,"palette":["#f98943","#f76a12","#291000","#5e402e","#fef8f4","","","#291000","",""],"typography":{"slug":"typo-default","global":{"font":"Sora","weight":"regular","size":"16","line":"1.6875","letter":"","word":""},"heading":{"font":"DM Serif Display","weight":"default","size":"","line":"1.3","letter":"","word":""}},"plugins":[{"name":"Elementor","slug":"elementor","init":"elementor\/elementor.php"},{"name":"Contact Form 7","slug":"contact-form-7","init":"contact-form-7\/wp-contact-form-7.php"}],"previews":{"small":{"src":"https:\/\/demo.themeoo.com\/wp-content\/uploads\/2022\/06\/digital-agency.jpg","loading":"lazy","srcset":"https:\/\/demo.themeoo.com\/wp-content\/uploads\/2022\/06\/digital-agency.jpg 1108w, https:\/\/demo.themeoo.com\/wp-content\/uploads\/2022\/06\/digital-agency-258x300.jpg 258w, https:\/\/demo.themeoo.com\/wp-content\/uploads\/2022\/06\/digital-agency-880x1024.jpg 880w, https:\/\/demo.themeoo.com\/wp-content\/uploads\/2022\/06\/digital-agency-768x894.jpg 768w, https:\/\/demo.themeoo.com\/wp-content\/uploads\/2022\/06\/digital-agency-400x466.jpg 400w, https:\/\/demo.themeoo.com\/wp-content\/uploads\/2022\/06\/digital-agency-259x302.jpg 259w, https:\/\/demo.themeoo.com\/wp-content\/uploads\/2022\/06\/digital-agency-554x645.jpg 554w","sizes":"(max-width: 1108px) 100vw, 1108px","width":"1108","height":"1290"},"large":{"src":"https:\/\/demo.themeoo.com\/wp-content\/uploads\/2022\/06\/digital-agency.jpg","loading":"lazy","srcset":"https:\/\/demo.themeoo.com\/wp-content\/uploads\/2022\/06\/digital-agency.jpg 1108w, https:\/\/demo.themeoo.com\/wp-content\/uploads\/2022\/06\/digital-agency-258x300.jpg 258w, https:\/\/demo.themeoo.com\/wp-content\/uploads\/2022\/06\/digital-agency-880x1024.jpg 880w, https:\/\/demo.themeoo.com\/wp-content\/uploads\/2022\/06\/digital-agency-768x894.jpg 768w, https:\/\/demo.themeoo.com\/wp-content\/uploads\/2022\/06\/digital-agency-400x466.jpg 400w, https:\/\/demo.themeoo.com\/wp-content\/uploads\/2022\/06\/digital-agency-259x302.jpg 259w, https:\/\/demo.themeoo.com\/wp-content\/uploads\/2022\/06\/digital-agency-554x645.jpg 554w","sizes":"(max-width: 1108px) 100vw, 1108px","width":"1108","height":"1290"}},"preview":"https:\/\/demo.themeoo.com\/agency\/?utm_source=ayyash-studio&utm_medium=wp-dash&utm_campaign=preview"},{"ID":83,"site":16,"name":"Dshanery Personal Portfolio","date":"2022-06-07 11:08:12","status":"publish","editor":"elementor","tags":[],"categories":["personal-site","portfolio-cv"],"is_pro":false,"views":21,"downloads":21,"palette":["#363a97","#181c80","#0e103e","#606367","#f5f6ff","","","","",""],"typography":{"slug":"typo-default","global":{"font":"Inter","weight":"regular","size":"16","line":"1.6","letter":"","word":""},"heading":{"font":"Jost","weight":"default","size":"","line":"1.3","letter":"","word":""}},"plugins":[{"name":"Elementor","slug":"elementor","init":"elementor\/elementor.php"},{"name":"Contact Form 7","slug":"contact-form-7","init":"contact-form-7\/wp-contact-form-7.php"},{"name":"MC4WP: Mailchimp for WordPress","slug":"mailchimp-for-wp","init":"mailchimp-for-wp\/mailchimp-for-wp.php"}],"previews":{"small":{"src":"https:\/\/demo.themeoo.com\/wp-content\/uploads\/2022\/06\/dshanery-personal-portfolio.jpg","loading":"lazy","srcset":"https:\/\/demo.themeoo.com\/wp-content\/uploads\/2022\/06\/dshanery-personal-portfolio.jpg 1108w, https:\/\/demo.themeoo.com\/wp-content\/uploads\/2022\/06\/dshanery-personal-portfolio-258x300.jpg 258w, https:\/\/demo.themeoo.com\/wp-content\/uploads\/2022\/06\/dshanery-personal-portfolio-880x1024.jpg 880w, https:\/\/demo.themeoo.com\/wp-content\/uploads\/2022\/06\/dshanery-personal-portfolio-768x894.jpg 768w, https:\/\/demo.themeoo.com\/wp-content\/uploads\/2022\/06\/dshanery-personal-portfolio-400x466.jpg 400w, https:\/\/demo.themeoo.com\/wp-content\/uploads\/2022\/06\/dshanery-personal-portfolio-259x302.jpg 259w, https:\/\/demo.themeoo.com\/wp-content\/uploads\/2022\/06\/dshanery-personal-portfolio-554x645.jpg 554w","sizes":"(max-width: 1108px) 100vw, 1108px","width":"1108","height":"1290"},"large":{"src":"https:\/\/demo.themeoo.com\/wp-content\/uploads\/2022\/06\/dshanery-personal-portfolio.jpg","loading":"lazy","srcset":"https:\/\/demo.themeoo.com\/wp-content\/uploads\/2022\/06\/dshanery-personal-portfolio.jpg 1108w, https:\/\/demo.themeoo.com\/wp-content\/uploads\/2022\/06\/dshanery-personal-portfolio-258x300.jpg 258w, https:\/\/demo.themeoo.com\/wp-content\/uploads\/2022\/06\/dshanery-personal-portfolio-880x1024.jpg 880w, https:\/\/demo.themeoo.com\/wp-content\/uploads\/2022\/06\/dshanery-personal-portfolio-768x894.jpg 768w, https:\/\/demo.themeoo.com\/wp-content\/uploads\/2022\/06\/dshanery-personal-portfolio-400x466.jpg 400w, https:\/\/demo.themeoo.com\/wp-content\/uploads\/2022\/06\/dshanery-personal-portfolio-259x302.jpg 259w, https:\/\/demo.themeoo.com\/wp-content\/uploads\/2022\/06\/dshanery-personal-portfolio-554x645.jpg 554w","sizes":"(max-width: 1108px) 100vw, 1108px","width":"1108","height":"1290"}},"preview":"https:\/\/demo.themeoo.com\/personal-portfolio\/?utm_source=ayyash-studio&utm_medium=wp-dash&utm_campaign=preview"},{"ID":85,"site":12,"name":"Wedding Invitation","date":"2022-06-07 11:06:56","status":"publish","editor":"elementor","tags":[],"categories":["community","wedding"],"is_pro":false,"views":98,"downloads":98,"palette":["#f98a43","#f76b12","#3a3a3a","#54595f","#d6d6d6","","#efe8e3","#ffffff","#f98943",""],"typography":{"slug":"typo-default","global":{"font":"Mulish","weight":"regular","size":"16","line":"1.6","letter":"","word":""},"heading":{"font":"Pacifico","weight":"regular","size":"","line":"1.3","letter":"","word":""}},"plugins":[{"name":"Elementor","slug":"elementor","init":"elementor\/elementor.php"},{"name":"Contact Form 7","slug":"contact-form-7","init":"contact-form-7\/wp-contact-form-7.php"}],"previews":{"small":{"src":"https:\/\/demo.themeoo.com\/wp-content\/uploads\/2022\/06\/wedding-scaled.jpg","loading":"lazy","srcset":"https:\/\/demo.themeoo.com\/wp-content\/uploads\/2022\/06\/wedding-scaled.jpg 2331w, https:\/\/demo.themeoo.com\/wp-content\/uploads\/2022\/06\/wedding-273x300.jpg 273w, https:\/\/demo.themeoo.com\/wp-content\/uploads\/2022\/06\/wedding-932x1024.jpg 932w, https:\/\/demo.themeoo.com\/wp-content\/uploads\/2022\/06\/wedding-768x844.jpg 768w, https:\/\/demo.themeoo.com\/wp-content\/uploads\/2022\/06\/wedding-1398x1536.jpg 1398w, https:\/\/demo.themeoo.com\/wp-content\/uploads\/2022\/06\/wedding-1865x2048.jpg 1865w, https:\/\/demo.themeoo.com\/wp-content\/uploads\/2022\/06\/wedding-400x439.jpg 400w, https:\/\/demo.themeoo.com\/wp-content\/uploads\/2022\/06\/wedding-275x302.jpg 275w, https:\/\/demo.themeoo.com\/wp-content\/uploads\/2022\/06\/wedding-554x608.jpg 554w, https:\/\/demo.themeoo.com\/wp-content\/uploads\/2022\/06\/wedding-600x659.jpg 600w","sizes":"(max-width: 2331px) 100vw, 2331px","width":"2331","height":"2560"},"large":{"src":"https:\/\/demo.themeoo.com\/wp-content\/uploads\/2022\/06\/wedding-scaled.jpg","loading":"lazy","srcset":"https:\/\/demo.themeoo.com\/wp-content\/uploads\/2022\/06\/wedding-scaled.jpg 2331w, https:\/\/demo.themeoo.com\/wp-content\/uploads\/2022\/06\/wedding-273x300.jpg 273w, https:\/\/demo.themeoo.com\/wp-content\/uploads\/2022\/06\/wedding-932x1024.jpg 932w, https:\/\/demo.themeoo.com\/wp-content\/uploads\/2022\/06\/wedding-768x844.jpg 768w, https:\/\/demo.themeoo.com\/wp-content\/uploads\/2022\/06\/wedding-1398x1536.jpg 1398w, https:\/\/demo.themeoo.com\/wp-content\/uploads\/2022\/06\/wedding-1865x2048.jpg 1865w, https:\/\/demo.themeoo.com\/wp-content\/uploads\/2022\/06\/wedding-400x439.jpg 400w, https:\/\/demo.themeoo.com\/wp-content\/uploads\/2022\/06\/wedding-275x302.jpg 275w, https:\/\/demo.themeoo.com\/wp-content\/uploads\/2022\/06\/wedding-554x608.jpg 554w, https:\/\/demo.themeoo.com\/wp-content\/uploads\/2022\/06\/wedding-600x659.jpg 600w","sizes":"(max-width: 2331px) 100vw, 2331px","width":"2331","height":"2560"}},"preview":"https:\/\/demo.themeoo.com\/wedding\/?utm_source=ayyash-studio&utm_medium=wp-dash&utm_campaign=preview"},{"ID":70,"site":15,"name":"Outdoor Adventure","date":"2022-06-07 10:59:38","status":"publish","editor":"elementor","tags":[],"categories":["blog","travel-blog"],"is_pro":false,"views":21,"downloads":21,"palette":["#e8614c","#e2381d","#312f41","#606367","#e8e8e8","","","#ffffff","",""],"typography":{"slug":"typo-default","global":{"font":"DM Sans","weight":"regular","size":"16","line":"1.6","letter":"","word":""},"heading":{"font":"DM Sans","weight":"default","size":"","line":"1.3","letter":"","word":""}},"plugins":[{"name":"Elementor","slug":"elementor","init":"elementor\/elementor.php"},{"name":"Contact Form 7","slug":"contact-form-7","init":"contact-form-7\/wp-contact-form-7.php"}],"previews":{"small":{"src":"https:\/\/demo.themeoo.com\/wp-content\/uploads\/2022\/06\/venturee-outdoor-adventure.jpg","loading":"lazy","srcset":"https:\/\/demo.themeoo.com\/wp-content\/uploads\/2022\/06\/venturee-outdoor-adventure.jpg 1108w, https:\/\/demo.themeoo.com\/wp-content\/uploads\/2022\/06\/venturee-outdoor-adventure-258x300.jpg 258w, https:\/\/demo.themeoo.com\/wp-content\/uploads\/2022\/06\/venturee-outdoor-adventure-880x1024.jpg 880w, https:\/\/demo.themeoo.com\/wp-content\/uploads\/2022\/06\/venturee-outdoor-adventure-768x894.jpg 768w, https:\/\/demo.themeoo.com\/wp-content\/uploads\/2022\/06\/venturee-outdoor-adventure-400x466.jpg 400w, https:\/\/demo.themeoo.com\/wp-content\/uploads\/2022\/06\/venturee-outdoor-adventure-259x302.jpg 259w, https:\/\/demo.themeoo.com\/wp-content\/uploads\/2022\/06\/venturee-outdoor-adventure-554x645.jpg 554w","sizes":"(max-width: 1108px) 100vw, 1108px","width":"1108","height":"1290"},"large":{"src":"https:\/\/demo.themeoo.com\/wp-content\/uploads\/2022\/06\/venturee-outdoor-adventure.jpg","loading":"lazy","srcset":"https:\/\/demo.themeoo.com\/wp-content\/uploads\/2022\/06\/venturee-outdoor-adventure.jpg 1108w, https:\/\/demo.themeoo.com\/wp-content\/uploads\/2022\/06\/venturee-outdoor-adventure-258x300.jpg 258w, https:\/\/demo.themeoo.com\/wp-content\/uploads\/2022\/06\/venturee-outdoor-adventure-880x1024.jpg 880w, https:\/\/demo.themeoo.com\/wp-content\/uploads\/2022\/06\/venturee-outdoor-adventure-768x894.jpg 768w, https:\/\/demo.themeoo.com\/wp-content\/uploads\/2022\/06\/venturee-outdoor-adventure-400x466.jpg 400w, https:\/\/demo.themeoo.com\/wp-content\/uploads\/2022\/06\/venturee-outdoor-adventure-259x302.jpg 259w, https:\/\/demo.themeoo.com\/wp-content\/uploads\/2022\/06\/venturee-outdoor-adventure-554x645.jpg 554w","sizes":"(max-width: 1108px) 100vw, 1108px","width":"1108","height":"1290"}},"preview":"https:\/\/demo.themeoo.com\/adventure\/?utm_source=ayyash-studio&utm_medium=wp-dash&utm_campaign=preview"},{"ID":66,"site":19,"name":"Shanroof Roofing Agency","date":"2022-06-07 10:54:23","status":"publish","editor":"elementor","tags":[],"categories":["local-business","roofing-services"],"is_pro":false,"views":15,"downloads":15,"palette":["#ff4747","#ff1f14","#1c1b1f","#5a606a","#f9f9f9","","#e9e9e9","","",""],"typography":{"slug":"typo-default","global":{"font":"Poppins","weight":"regular","size":"16","line":"1.6","letter":"","word":""},"heading":{"font":"Poppins","weight":"default","size":"","line":"1.3","letter":"","word":""}},"plugins":[{"name":"Elementor","slug":"elementor","init":"elementor\/elementor.php"},{"name":"Contact Form 7","slug":"contact-form-7","init":"contact-form-7\/wp-contact-form-7.php"}],"previews":{"small":{"src":"https:\/\/demo.themeoo.com\/wp-content\/uploads\/2022\/06\/shanroof-roofing-agency.jpg","loading":"lazy","srcset":"https:\/\/demo.themeoo.com\/wp-content\/uploads\/2022\/06\/shanroof-roofing-agency.jpg 1108w, https:\/\/demo.themeoo.com\/wp-content\/uploads\/2022\/06\/shanroof-roofing-agency-258x300.jpg 258w, https:\/\/demo.themeoo.com\/wp-content\/uploads\/2022\/06\/shanroof-roofing-agency-880x1024.jpg 880w, https:\/\/demo.themeoo.com\/wp-content\/uploads\/2022\/06\/shanroof-roofing-agency-768x894.jpg 768w, https:\/\/demo.themeoo.com\/wp-content\/uploads\/2022\/06\/shanroof-roofing-agency-400x466.jpg 400w, https:\/\/demo.themeoo.com\/wp-content\/uploads\/2022\/06\/shanroof-roofing-agency-259x302.jpg 259w, https:\/\/demo.themeoo.com\/wp-content\/uploads\/2022\/06\/shanroof-roofing-agency-554x645.jpg 554w","sizes":"(max-width: 1108px) 100vw, 1108px","width":"1108","height":"1290"},"large":{"src":"https:\/\/demo.themeoo.com\/wp-content\/uploads\/2022\/06\/shanroof-roofing-agency.jpg","loading":"lazy","srcset":"https:\/\/demo.themeoo.com\/wp-content\/uploads\/2022\/06\/shanroof-roofing-agency.jpg 1108w, https:\/\/demo.themeoo.com\/wp-content\/uploads\/2022\/06\/shanroof-roofing-agency-258x300.jpg 258w, https:\/\/demo.themeoo.com\/wp-content\/uploads\/2022\/06\/shanroof-roofing-agency-880x1024.jpg 880w, https:\/\/demo.themeoo.com\/wp-content\/uploads\/2022\/06\/shanroof-roofing-agency-768x894.jpg 768w, https:\/\/demo.themeoo.com\/wp-content\/uploads\/2022\/06\/shanroof-roofing-agency-400x466.jpg 400w, https:\/\/demo.themeoo.com\/wp-content\/uploads\/2022\/06\/shanroof-roofing-agency-259x302.jpg 259w, https:\/\/demo.themeoo.com\/wp-content\/uploads\/2022\/06\/shanroof-roofing-agency-554x645.jpg 554w","sizes":"(max-width: 1108px) 100vw, 1108px","width":"1108","height":"1290"}},"preview":"https:\/\/demo.themeoo.com\/roofing-agency\/?utm_source=ayyash-studio&utm_medium=wp-dash&utm_campaign=preview"},{"ID":56,"site":10,"name":"Interior Studio","date":"2022-06-07 09:49:29","status":"publish","editor":"elementor","tags":[],"categories":["interior-designer","professionals"],"is_pro":false,"views":20,"downloads":18,"palette":["#60be02","#d8f366","#171b07","#54595f","#f4f5f0","","","","",""],"typography":{"slug":"typo-default","global":{"font":"Inter","weight":"regular","size":"16","line":"1.6","letter":"","word":""},"heading":{"font":"Rokkitt","weight":"700","size":"","line":"1","letter":"","word":""}},"plugins":[{"name":"Elementor","slug":"elementor","init":"elementor\/elementor.php"},{"name":"Contact Form 7","slug":"contact-form-7","init":"contact-form-7\/wp-contact-form-7.php"}],"previews":{"small":{"src":"https:\/\/demo.themeoo.com\/wp-content\/uploads\/2022\/06\/interior-design.jpg","loading":"lazy","srcset":"https:\/\/demo.themeoo.com\/wp-content\/uploads\/2022\/06\/interior-design.jpg 1108w, https:\/\/demo.themeoo.com\/wp-content\/uploads\/2022\/06\/interior-design-258x300.jpg 258w, https:\/\/demo.themeoo.com\/wp-content\/uploads\/2022\/06\/interior-design-880x1024.jpg 880w, https:\/\/demo.themeoo.com\/wp-content\/uploads\/2022\/06\/interior-design-768x894.jpg 768w, https:\/\/demo.themeoo.com\/wp-content\/uploads\/2022\/06\/interior-design-400x466.jpg 400w, https:\/\/demo.themeoo.com\/wp-content\/uploads\/2022\/06\/interior-design-259x302.jpg 259w, https:\/\/demo.themeoo.com\/wp-content\/uploads\/2022\/06\/interior-design-554x645.jpg 554w, https:\/\/demo.themeoo.com\/wp-content\/uploads\/2022\/06\/interior-design-600x699.jpg 600w","sizes":"(max-width: 1108px) 100vw, 1108px","width":"1108","height":"1290"},"large":{"src":"https:\/\/demo.themeoo.com\/wp-content\/uploads\/2022\/06\/interior-design.jpg","loading":"lazy","srcset":"https:\/\/demo.themeoo.com\/wp-content\/uploads\/2022\/06\/interior-design.jpg 1108w, https:\/\/demo.themeoo.com\/wp-content\/uploads\/2022\/06\/interior-design-258x300.jpg 258w, https:\/\/demo.themeoo.com\/wp-content\/uploads\/2022\/06\/interior-design-880x1024.jpg 880w, https:\/\/demo.themeoo.com\/wp-content\/uploads\/2022\/06\/interior-design-768x894.jpg 768w, https:\/\/demo.themeoo.com\/wp-content\/uploads\/2022\/06\/interior-design-400x466.jpg 400w, https:\/\/demo.themeoo.com\/wp-content\/uploads\/2022\/06\/interior-design-259x302.jpg 259w, https:\/\/demo.themeoo.com\/wp-content\/uploads\/2022\/06\/interior-design-554x645.jpg 554w, https:\/\/demo.themeoo.com\/wp-content\/uploads\/2022\/06\/interior-design-600x699.jpg 600w","sizes":"(max-width: 1108px) 100vw, 1108px","width":"1108","height":"1290"}},"preview":"https:\/\/demo.themeoo.com\/interior\/?utm_source=ayyash-studio&utm_medium=wp-dash&utm_campaign=preview"}]